djangocms_charts/__init__.py
djangocms_charts/admin.py
djangocms_charts/apps.py
djangocms_charts/cache.py
djangocms_charts/cms_plugins.py
djangocms_charts/consts.py
djangocms_charts/forms.py
djangocms_charts/migration_utils.py
djangocms_charts/models.py
djangocms_charts/models_axes.py
djangocms_charts/models_colors.py
djangocms_charts/models_datasets.py
djangocms_charts/models_options.py
djangocms_charts/tests.py
djangocms_charts/urls.py
djangocms_charts/utils.py
djangocms_charts/views.py
djangocms_charts/widgets.py
djangocms_charts/migrations/0001_initial.py
djangocms_charts/migrations/0002_add_chart_position.py
djangocms_charts/migrations/0003_auto_20190201_1645.py
djangocms_charts/migrations/0004_auto_20200521_2007.py
djangocms_charts/migrations/0005_complete_refactor.py
djangocms_charts/migrations/0006_migrate_old_chart_data.py
djangocms_charts/migrations/0007_migrate_old_chart_options.py
djangocms_charts/migrations/0008_set_new_chart_options.py
djangocms_charts/migrations/0009_remove_old_charts.py
djangocms_charts/migrations/0010_auto_20201106_1834.py
djangocms_charts/migrations/__init__.py
djangocms_charts/static/djangocms_charts/img/chart-icon.png
djangocms_charts/static/djangocms_charts/input/css/handsontable.full.modified.css
djangocms_charts/static/djangocms_charts/input/css/handsontable.full.modified.min.css
djangocms_charts/static/djangocms_charts/input/css/jquery.contextMenu.css
djangocms_charts/static/djangocms_charts/input/css/jquery.contextMenu.min.css
djangocms_charts/static/djangocms_charts/input/custom/admin_fixes.js
djangocms_charts/static/djangocms_charts/input/custom/admin_fixes.min.js
djangocms_charts/static/djangocms_charts/input/custom/admin_styles.css
djangocms_charts/static/djangocms_charts/input/custom/admin_styles.min.css
djangocms_charts/static/djangocms_charts/input/custom/multi-color-select.js
djangocms_charts/static/djangocms_charts/input/custom/multi-color-select.min.js
djangocms_charts-3.0.4.dist-info/LICENSE
djangocms_charts-3.0.4.dist-info/METADATA
djangocms_charts-3.0.4.dist-info/WHEEL
djangocms_charts-3.0.4.dist-info/top_level.txt
djangocms_charts-3.0.4.dist-info/RECORD
