Metadata-Version: 2.1
Name: djangocms-charts
Version: 3.0.4
Summary: DjangoCMS Plugin to add and edit ChartJs charts
Home-page: https://github.com/mcldev/djangocms-charts
Author: Michael Carder Ltd
License: MIT License
Classifier: Environment :: Web Environment
Classifier: Intended Audience :: Developers
Classifier: License :: OSI Approved :: MIT License
Classifier: Operating System :: OS Independent
Classifier: Framework :: Django
Classifier: Framework :: Django :: 2.2
Classifier: Programming Language :: Python :: 3
Classifier: Programming Language :: Python :: 3.4
Classifier: Programming Language :: Python :: 3.5
Classifier: Programming Language :: Python :: 3.6
Classifier: Programming Language :: Python :: 3.7
Classifier: Programming Language :: Python :: 3.8
Classifier: Topic :: Internet :: WWW/HTTP
Classifier: Topic :: Internet :: WWW/HTTP :: Dynamic Content
License-File: LICENSE
Requires-Dist: django (>=2.2)
Requires-Dist: django-cms (>=3.4)
Requires-Dist: django-select2
